restpki_client/__init__.py
restpki_client/apis.py
restpki_client/authentication.py
restpki_client/authentication_result.py
restpki_client/blob_reference.py
restpki_client/cades_signature.py
restpki_client/cades_signature_finisher.py
restpki_client/cades_signature_starter.py
restpki_client/color.py
restpki_client/detached_resource_xml_signature_starter.py
restpki_client/digest_algorithm.py
restpki_client/digest_algorithm_and_value.py
restpki_client/enum.py
restpki_client/file_reference.py
restpki_client/file_result.py
restpki_client/full_xml_signature_starter.py
restpki_client/name.py
restpki_client/namespace_manager.py
restpki_client/oids.py
restpki_client/online_resource_xml_signature_starter.py
restpki_client/pades_certification_level.py
restpki_client/pades_horizontal_align.py
restpki_client/pades_measurement_units.py
restpki_client/pades_page_optimization.py
restpki_client/pades_signature.py
restpki_client/pades_signature_explorer.py
restpki_client/pades_signature_finisher.py
restpki_client/pades_signature_starter.py
restpki_client/pades_signer_info.py
restpki_client/pades_size.py
restpki_client/pades_visual_positioning_presets.py
restpki_client/pades_visual_rectangle.py
restpki_client/page_orientations.py
restpki_client/paper_sizes.py
restpki_client/pdf_container_definition.py
restpki_client/pdf_helper.py
restpki_client/pdf_mark.py
restpki_client/pdf_mark_element.py
restpki_client/pdf_mark_element_type.py
restpki_client/pdf_mark_image.py
restpki_client/pdf_mark_image_element.py
restpki_client/pdf_mark_page_options.py
restpki_client/pdf_mark_qr_code_element.py
restpki_client/pdf_mark_text_element.py
restpki_client/pdf_marker.py
restpki_client/pdf_text_section.py
restpki_client/pdf_text_style.py
restpki_client/pk_algorithm.py
restpki_client/pk_certificate.py
restpki_client/pki_brazil_certificate_fields.py
restpki_client/pki_italy_certificate_fields.py
restpki_client/resource_content_or_reference.py
restpki_client/rest_base_error.py
restpki_client/rest_error.py
restpki_client-1.2.1.dist-info/METADATA
restpki_client-1.2.1.dist-info/WHEEL
restpki_client-1.2.1.dist-info/top_level.txt
restpki_client-1.2.1.dist-info/RECORD
